md2pdf/__init__.py
md2pdf/__main__.py
md2pdf/cli.py
md2pdf/conf.py
md2pdf/core.py
md2pdf/exceptions.py
md2pdf-3.1.0.dist-info/METADATA
md2pdf-3.1.0.dist-info/WHEEL
md2pdf-3.1.0.dist-info/entry_points.txt
md2pdf-3.1.0.dist-info/licenses/LICENSE
md2pdf-3.1.0.dist-info/RECORD
