Metadata-Version: 2.4
Name: md2pdf
Version: 3.1.0
Summary: The Markdown to PDF conversion tool with styles
Project-URL: Homepage, https://github.com/jmaupetit/md2pdf
Project-URL: Repository, https://github.com/jmaupetit/md2pdf
Author-email: Julien Maupetit <julien@maupetit.net>
License-Expression: MIT
License-File: LICENSE
Keywords: cli,css,html,markdown,pdf
Classifier: Development Status :: 5 - Production/Stable
Classifier: Environment :: Console
Classifier: Intended Audience :: Developers
Classifier: License :: OSI Approved :: MIT License
Classifier: Operating System :: MacOS
Classifier: Operating System :: Microsoft :: Windows
Classifier: Operating System :: POSIX
Classifier: Programming Language :: Python :: 3.10
Classifier: Programming Language :: Python :: 3.11
Classifier: Programming Language :: Python :: 3.12
Classifier: Programming Language :: Python :: 3.13
Classifier: Programming Language :: Python :: 3.14
Classifier: Topic :: Office/Business
Classifier: Topic :: Utilities
Requires-Python: >=3.10
Requires-Dist: jinja2>=3
Requires-Dist: markdown>=3.5
Requires-Dist: pygments>=2.17
Requires-Dist: pymdown-extensions>=10
Requires-Dist: python-frontmatter>=1.1
Requires-Dist: weasyprint>=60
Provides-Extra: cli
Requires-Dist: typer>=0.21.1; extra == 'cli'
Requires-Dist: watchfiles>=1.1.1; extra == 'cli'
Provides-Extra: latex
Requires-Dist: markdown-katex>=202406.1035; extra == 'latex'
